setup.py
pDtlabCsCovea/_init_.py
pDtlabCsCovea.egg-info/PKG-INFO
pDtlabCsCovea.egg-info/SOURCES.txt
pDtlabCsCovea.egg-info/dependency_links.txt
pDtlabCsCovea.egg-info/not-zip-safe
pDtlabCsCovea.egg-info/top_level.txt